config/__init__.py
config/default.py
config/drone-ci.py
netranker/__init__.py
netranker/app.py
netranker/card_storage.py
netranker/core.py
netranker/result_storage.py
netranker/utils.py
netranker-0.0.3.dist-info/LICENSE
netranker-0.0.3.dist-info/METADATA
netranker-0.0.3.dist-info/WHEEL
netranker-0.0.3.dist-info/entry_points.txt
netranker-0.0.3.dist-info/top_level.txt
netranker-0.0.3.dist-info/RECORD
