Metadata-Version: 2.1
Name: netranker
Version: 0.0.3
Summary: Flask APIs for netranker
Home-page: https://github.com/ouroboros8/netranker
Author: Daniel Strong
Author-email: dstrong@glyx.co.uk
License: UNKNOWN
Platform: UNKNOWN
Classifier: Programming Language :: Python :: 3
Classifier: License :: OSI Approved :: GNU General Public License v3 or later (GPLv3+)
Classifier: Operating System :: OS Independent
Requires-Python: >=3.5
Requires-Dist: flask
Requires-Dist: flask-restful
Requires-Dist: PyJWT
Requires-Dist: pymongo
